MirKusAnalytics/__init__.py
MirKusAnalytics/dataModels.py
MirKusAnalytics/db.py
MirKusAnalytics/logger.py
mirkusanalytics-1.1.0.dist-info/licenses/LICENSE
mirkusanalytics-1.1.0.dist-info/METADATA
mirkusanalytics-1.1.0.dist-info/WHEEL
mirkusanalytics-1.1.0.dist-info/top_level.txt
mirkusanalytics-1.1.0.dist-info/RECORD
