Metadata-Version: 2.4
Name: MirKusAnalytics
Version: 1.1.0
Summary: Private analytics tools
Author-email: "MirKus Inc." <information@mirkus.com>
License-Expression: MIT
License-File: LICENSE
Requires-Dist: pandas
Requires-Dist: SQLAlchemy
Requires-Dist: python-dotenv
Requires-Dist: pyodbc
Dynamic: license-file
